FSK2/rtl/full_wave_rectifier.v
module full_wave_rectifier (
    //全波整流器
    input  wire [15:0] ac_signal,  // 交流输入（有符号数）
    output wire [15:0] dc_output   // 整流后输出（绝对值）
);

assign dc_output = ac_signal[15] ? (~ac_signal) : ac_signal ; 

endmodule

2ASK/rtl/double_ask_rx.v
module double_ask_rx (
    input   wire        sys_clk,      // 50MHz系统时钟
    input   wire        sys_rst_n,    // 异步复位
    input   wire [15:0] rx_signal,    // 接收信号（来自发射端tx）
    output  reg         data_out,     // 解调数据输出
    output  reg         data_valid    // 数据有效标志
);

//===== 参数定义 =====//
parameter SYMBOL_PERIOD  = 50;        // 符号周期（50个时钟=1us）
parameter THRESHOLD      = 32'd0001_0000; // 判决门限（需根据实际调整）

//===== 信号声明 =====//
wire [15:0] rectified;                // 整流后信号
reg  [31:0] integrator;               // 积分器（32位防止溢出）
reg  [15:0] symbol_counter;           // 符号周期计数器
wire [31:0] averaged;                 // 积分平均值

//===== 全波整流模块实例化 =====//
full_wave_rectifier rectifier (
    .ac_signal(rx_signal),
    .dc_output(rectified)
);

//===== 积分与判决逻辑 =====//
always @(posedge sys_clk or negedge sys_rst_n) begin
    if (!sys_rst_n) begin
        integrator      <= 32'd0;
        symbol_counter  <= 16'd0;
        data_out        <= 1'b0;
        data_valid      <= 1'b0;
    end else begin
        // 积分器累加
        integrator <= integrator + {16'd0, rectified};
        
        // 符号周期计数
        if (symbol_counter == SYMBOL_PERIOD-1) begin
            // 计算平均值并判决
            data_out   <= (averaged > THRESHOLD) ? 1'b1 : 1'b0;
            data_valid <= 1'b1;
            
            // 复位计数器
            symbol_counter <= 16'd0;
            integrator     <= 32'd0;
        end else begin
            symbol_counter <= symbol_counter + 16'd1;
            data_valid     <= 1'b0;
        end
    end
end

//===== 积分平均值计算 =====//
assign averaged = integrator / SYMBOL_PERIOD;

endmodule

2ASK/rtl/sine_lut.v
module sine_lut (
    input   wire        sys_clk,     // 50MHz时钟
    input   wire        sys_rst_n,   // 复位

    output  reg [15:0]  q     // Q1.15格式正弦波输出
);

//===== 参数定义 =====//
parameter CLK_FREQ  = 50_000_000;  // 50MHz
parameter WAVE_FREQ = 1_000_000;   // 目标频率1MHz
parameter LUT_POINTS = 32;         // 32点LUT

//----- 相位累加器步长计算 -----//
// 公式：Phase_Step = (WAVE_FREQ * 2^32) / CLK_FREQ
localparam PHASE_STEP = (WAVE_FREQ * 64'd4294967296) / CLK_FREQ;  // 计算结果：85,899,345

//===== 相位累加器 =====//
reg [31:0] phase_acc;  // 32位相位累加器

always @(posedge sys_clk or negedge sys_rst_n) begin
    if (!sys_rst_n)
        phase_acc <= 32'd0;
    else
        phase_acc <= phase_acc + PHASE_STEP;  // 相位累加
end

//===== LUT索引生成（取高5位）=====//
wire [4:0] lut_index = phase_acc[31:27];  // 32点LUT需要5位地址

//===== 32点正弦波LUT（Q1.15格式）=====//
always @(posedge sys_clk) begin
    case(lut_index)
        5'd0:  q <= 16'h0000;  5'd1:  q <= 16'h18F9;
        5'd2:  q <= 16'h30FB;  5'd3:  q <= 16'h471C;
        5'd4:  q <= 16'h5A82;  5'd5:  q <= 16'h6A6D;
        5'd6:  q <= 16'h7641;  5'd7:  q <= 16'h7D89;
        5'd8:  q <= 16'h7FF6;  5'd9:  q <= 16'h7D89;
        5'd10: q <= 16'h7641;  5'd11: q <= 16'h6A6D;
        5'd12: q <= 16'h5A82;  5'd13: q <= 16'h471C;
        5'd14: q <= 16'h30FB;  5'd15: q <= 16'h18F9;
        5'd16: q <= 16'h0000;  5'd17: q <= 16'hE707;
        5'd18: q <= 16'hCF05;  5'd19: q <= 16'hB8E4;
        5'd20: q <= 16'hA57E;  5'd21: q <= 16'h9593;
        5'd22: q <= 16'h89BF;  5'd23: q <= 16'h8277;
        5'd24: q <= 16'h800A;  5'd25: q <= 16'h8277;
        5'd26: q <= 16'h89BF;  5'd27: q <= 16'h9593;
        5'd28: q <= 16'hA57E;  5'd29: q <= 16'hB8E4;
        5'd30: q <= 16'hCF05;  5'd31: q <= 16'hE707;
        default: q <= 16'h0000;
    endcase
end


endmodule

2ASK/rtl/double_ask_tx.v
module double_ask_tx
#(
    parameter B_FREQ = 'd49
)
(
    input   wire                sys_clk         ,
    input   wire                sys_rst_n       ,
    input   wire    [15:0]      sine_val        ,
    input   wire    [15:0]      data_in         ,

    output  wire    [15:0]      mod_out         
);

reg [15:0]  data_in_reg     ;
reg [4:0]   data_cnt        ;
reg [5:0]   freq_cnt        ;
wire        data_valid      ;
wire        st_sign         ;


//data_in_reg 对data_in打拍 同步时序
always @(posedge sys_clk or negedge sys_rst_n) begin
    if (~sys_rst_n) begin
        data_in_reg <= 'b0;
    end
    else
        data_in_reg <= data_in;
end

//data_cnt  取单极性非零信号
always @(posedge sys_clk or negedge sys_rst_n) begin
    if (~sys_rst_n) begin
        data_cnt <= 'd0; 
    end
    else if (data_in != data_in_reg ) begin //在这里已经写了data_valid拉高判据 为了保持持续 使用计数器作为data_valid的高电平判据  当新数据到来时重置计数器为1
        data_cnt <= 'd1;
    end
    else if (data_cnt >= 'd0 && data_cnt <= 'd16 && freq_cnt == B_FREQ) begin
        data_cnt <= data_cnt + 'd1;
    end
    else
        data_cnt <= data_cnt;
end


//freq_cnt 周期计数 用于载波扩展  50 MHZ / 50
always @(posedge sys_clk or negedge sys_rst_n) begin
    if (~sys_rst_n) begin
        freq_cnt <= 'd0;
    end
    else if ((data_in !=data_in_reg) || freq_cnt == B_FREQ) begin
        freq_cnt <= 'd0;
    end
    else
        freq_cnt <= freq_cnt + 'd1;
end

//data_valid 第一次新传入数据有效时拉高
assign data_valid =  (data_cnt>= 'd1 && data_cnt <='d16) ? 1'b1 : 1'b0;

//输出st信号 测试用
assign st_sign = data_valid ? (data_in_reg[16 - data_cnt]): 1'b1 ; 

//mod_out 数据有效data_valid高电平则使用data_in 无则默认1调制
assign mod_out  = data_valid ? (data_in_reg[16 - data_cnt] ?  sine_val : 'b0) : sine_val ; 
endmodule

2ASK/rtl/double_ask_tx_top.v
module double_ask_tx_top (
    input   wire                sys_clk     ,
    input   wire                sys_rst_n   ,
    input   wire    [15:0]      data_in     ,

    output  wire    [15:0]      tx          
);

wire [15:0]          sine_val    ;

double_ask_tx double_ask_tx_inst(
    .sys_clk         (sys_clk   ),
    .sys_rst_n       (sys_rst_n ),
    .sine_val        (sine_val  ),
    .data_in         (data_in   ),

    .mod_out         (tx        )
);

sine_lut sine_lut_inst(
    .sys_clk         (sys_clk   ),
    .sys_rst_n       (sys_rst_n ),

    .q               (sine_val  )
);





endmodule

2ASK/rtl/top_double_ask.v
module top_double_ask (
    input   wire        sys_clk,     // 50MHz系统时钟
    input   wire        sys_rst_n,   // 异步复位
    input   wire [15:0] data_in,     // 输入数据
    output  wire        data_out,    // 解调输出
    output  wire        data_valid   // 数据有效标志
);

//===== 内部信号声明 =====//
wire [15:0] tx_signal;  // 发射信号

//===== 发射端实例化 =====//
double_ask_tx_top tx_inst (
    .sys_clk    (sys_clk),
    .sys_rst_n  (sys_rst_n),
    .data_in    (data_in),
    .tx         (tx_signal)
);

//===== 接收端实例化 =====//
double_ask_rx rx_inst (
    .sys_clk    (sys_clk),
    .sys_rst_n  (sys_rst_n),
    .rx_signal  (tx_signal),  // 直接连接发射输出到接收输入
    .data_out   (data_out),
    .data_valid (data_valid)
);

endmodule

2ASK/sim/tb_top_double_ask.v
`timescale 1ns/1ns
module tb_top_double_ask();

//===== 参数定义 =====//
parameter CLK_PERIOD = 20;  // 50MHz时钟周期

//===== 信号声明 =====//
reg         sys_clk;
reg         sys_rst_n;
reg  [15:0] data_in;
wire        data_out;
wire        data_valid;

//===== 顶层模块实例化 =====//
top_double_ask uut (
    .sys_clk    (sys_clk),
    .sys_rst_n  (sys_rst_n),
    .data_in    (data_in),
    .data_out   (data_out),
    .data_valid (data_valid)
);

//===== 时钟生成 =====//
initial begin
    sys_clk = 1'b0;
    forever #(CLK_PERIOD/2) sys_clk = ~sys_clk;
end

//===== 测试激励生成 =====//
initial begin
    // 初始化
    sys_rst_n = 1'b0;
    data_in = 16'h0000;
    #100
    sys_rst_n = 1'b1;
    
    // 测试用例1：发送16'hABCD
    #(20*16*50) 
    data_in = 16'hABCD;
    #(20*16*50)  // 等待1us（1个符号周期）

    data_in = 16'h1234;
    
end

//===== 波形监视 =====//
initial begin
    $dumpfile("wave.vcd");
    $dumpvars(0, tb_top_double_ask);
    $monitor("Time=%t, DataIn=%h, DataOut=%b, Valid=%b", 
             $time, data_in, data_out, data_valid);
end

endmodule

2ASK/quartus_prj/simulation/modelsim/wave.vcd
$date
	Sat Feb 22 17:04:03 2025
$end
$version
	ModelSim Version 10.4
$end
$timescale
	1ps
$end

$scope module tb_top_double_ask $end
$var parameter 32 ! CLK_PERIOD $end
$var reg 1 " sys_clk $end
$var reg 1 # sys_rst_n $end
$var reg 16 $ data_in [15:0] $end
$var wire 1 % data_out $end
$var wire 1 & data_valid $end

$scope module uut $end
$var wire 1 ' sys_clk $end
$var wire 1 ( sys_rst_n $end
$var wire 1 ) data_in [15] $end
$var wire 1 * data_in [14] $end
$var wire 1 + data_in [13] $end
$var wire 1 , data_in [12] $end
$var wire 1 - data_in [11] $end
$var wire 1 . data_in [10] $end
$var wire 1 / data_in [9] $end
$var wire 1 0 data_in [8] $end
$var wire 1 1 data_in [7] $end
$var wire 1 2 data_in [6] $end
$var wire 1 3 data_in [5] $end
$var wire 1 4 data_in [4] $end
$var wire 1 5 data_in [3] $end
$var wire 1 6 data_in [2] $end
$var wire 1 7 data_in [1] $end
$var wire 1 8 data_in [0] $end
$var wire 1 % data_out $end
$var wire 1 & data_valid $end
$var wire 1 9 tx_signal [15] $end
$var wire 1 : tx_signal [14] $end
$var wire 1 ; tx_signal [13] $end
$var wire 1 < tx_signal [12] $end
$var wire 1 = tx_signal [11] $end
$var wire 1 > tx_signal [10] $end
$var wire 1 ? tx_signal [9] $end
$var wire 1 @ tx_signal [8] $end
$var wire 1 A tx_signal [7] $end
$var wire 1 B tx_signal [6] $end
$var wire 1 C tx_signal [5] $end
$var wire 1 D tx_signal [4] $end
$var wire 1 E tx_signal [3] $end
$var wire 1 F tx_signal [2] $end
$var wire 1 G tx_signal [1] $end
$var wire 1 H tx_signal [0] $end

$scope module tx_inst $end
$var wire 1 ' sys_clk $end
$var wire 1 ( sys_rst_n $end
$var wire 1 ) data_in [15] $end
$var wire 1 * data_in [14] $end
$var wire 1 + data_in [13] $end
$var wire 1 , data_in [12] $end
$var wire 1 - data_in [11] $end
$var wire 1 . data_in [10] $end
$var wire 1 / data_in [9] $end
$var wire 1 0 data_in [8] $end
$var wire 1 1 data_in [7] $end
$var wire 1 2 data_in [6] $end
$var wire 1 3 data_in [5] $end
$var wire 1 4 data_in [4] $end
$var wire 1 5 data_in [3] $end
$var wire 1 6 data_in [2] $end
$var wire 1 7 data_in [1] $end
$var wire 1 8 data_in [0] $end
$var wire 1 9 tx [15] $end
$var wire 1 : tx [14] $end
$var wire 1 ; tx [13] $end
$var wire 1 < tx [12] $end
$var wire 1 = tx [11] $end
$var wire 1 > tx [10] $end
$var wire 1 ? tx [9] $end
$var wire 1 @ tx [8] $end
$var wire 1 A tx [7] $end
$var wire 1 B tx [6] $end
$var wire 1 C tx [5] $end
$var wire 1 D tx [4] $end
$var wire 1 E tx [3] $end
$var wire 1 F tx [2] $end
$var wire 1 G tx [1] $end
$var wire 1 H tx [0] $end
$var wire 1 I sine_val [15] $end
$var wire 1 J sine_val [14] $end
$var wire 1 K sine_val [13] $end
$var wire 1 L sine_val [12] $end
$var wire 1 M sine_val [11] $end
$var wire 1 N sine_val [10] $end
$var wire 1 O sine_val [9] $end
$var wire 1 P sine_val [8] $end
$var wire 1 Q sine_val [7] $end
$var wire 1 R sine_val [6] $end
$var wire 1 S sine_val [5] $end
$var wire 1 T sine_val [4] $end
$var wire 1 U sine_val [3] $end
$var wire 1 V sine_val [2] $end
$var wire 1 W sine_val [1] $end
$var wire 1 X sine_val [0] $end

$scope module double_ask_tx_inst $end
$var parameter 32 Y B_FREQ $end
$var wire 1 ' sys_clk $end
$var wire 1 ( sys_rst_n $end
$var wire 1 I sine_val [15] $end
$var wire 1 J sine_val [14] $end
$var wire 1 K sine_val [13] $end
$var wire 1 L sine_val [12] $end
$var wire 1 M sine_val [11] $end
$var wire 1 N sine_val [10] $end
$var wire 1 O sine_val [9] $end
$var wire 1 P sine_val [8] $end
$var wire 1 Q sine_val [7] $end
$var wire 1 R sine_val [6] $end
$var wire 1 S sine_val [5] $end
$var wire 1 T sine_val [4] $end
$var wire 1 U sine_val [3] $end
$var wire 1 V sine_val [2] $end
$var wire 1 W sine_val [1] $end
$var wire 1 X sine_val [0] $end
$var wire 1 ) data_in [15] $end
$var wire 1 * data_in [14] $end
$var wire 1 + data_in [13] $end
$var wire 1 , data_in [12] $end
$var wire 1 - data_in [11] $end
$var wire 1 . data_in [10] $end
$var wire 1 / data_in [9] $end
$var wire 1 0 data_in [8] $end
$var wire 1 1 data_in [7] $end
$var wire 1 2 data_in [6] $end
$var wire 1 3 data_in [5] $end
$var wire 1 4 data_in [4] $end
$var wire 1 5 data_in [3] $end
$var wire 1 6 data_in [2] $end
$var wire 1 7 data_in [1] $end
$var wire 1 8 data_in [0] $end
$var wire 1 9 mod_out [15] $end
$var wire 1 : mod_out [14] $end
$var wire 1 ; mod_out [13] $end
$var wire 1 < mod_out [12] $end
$var wire 1 = mod_out [11] $end
$var wire 1 > mod_out [10] $end
$var wire 1 ? mod_out [9] $end
$var wire 1 @ mod_out [8] $end
$var wire 1 A mod_out [7] $end
$var wire 1 B mod_out [6] $end
$var wire 1 C mod_out [5] $end
$var wire 1 D mod_out [4] $end
$var wire 1 E mod_out [3] $end
$var wire 1 F mod_out [2] $end
$var wire 1 G mod_out [1] $end
$var wire 1 H mod_out [0] $end
$var reg 16 Z data_in_reg [15:0] $end
$var reg 5 [ data_cnt [4:0] $end
$var reg 6 \ freq_cnt [5:0] $end
$var wire 1 ] data_valid $end
$var wire 1 ^ st_sign $end
$upscope $end

$scope module sine_lut_inst $end
$var parameter 32 _ CLK_FREQ $end
$var parameter 32 ` WAVE_FREQ $end
$var parameter 32 a LUT_POINTS $end
$var parameter 64 b PHASE_STEP $end
$var wire 1 ' sys_clk $end
$var wire 1 ( sys_rst_n $end
$var reg 16 c q [15:0] $end
$var reg 32 d phase_acc [31:0] $end
$var wire 1 e lut_index [4] $end
$var wire 1 f lut_index [3] $end
$var wire 1 g lut_index [2] $end
$var wire 1 h lut_index [1] $end
$var wire 1 i lut_index [0] $end
$upscope $end
$upscope $end

$scope module rx_inst $end
$var parameter 32 j SYMBOL_PERIOD $end
$var parameter 32 k THRESHOLD $end
$var wire 1 ' sys_clk $end
$var wire 1 ( sys_rst_n $end
$var wire 1 9 rx_signal [15] $end
$var wire 1 : rx_signal [14] $end
$var wire 1 ; rx_signal [13] $end
$var wire 1 < rx_signal [12] $end
$var wire 1 = rx_signal [11] $end
$var wire 1 > rx_signal [10] $end
$var wire 1 ? rx_signal [9] $end
$var wire 1 @ rx_signal [8] $end
$var wire 1 A rx_signal [7] $end
$var wire 1 B rx_signal [6] $end
$var wire 1 C rx_signal [5] $end
$var wire 1 D rx_signal [4] $end
$var wire 1 E rx_signal [3] $end
$var wire 1 F rx_signal [2] $end
$var wire 1 G rx_signal [1] $end
$var wire 1 H rx_signal [0] $end
$var reg 1 l data_out $end
$var reg 1 m data_valid $end
$var wire 1 n rectified [15] $end
$var wire 1 o rectified [14] $end
$var wire 1 p rectified [13] $end
$var wire 1 q rectified [12] $end
$var wire 1 r rectified [11] $end
$var wire 1 s rectified [10] $end
$var wire 1 t rectified [9] $end
$var wire 1 u rectified [8] $end
$var wire 1 v rectified [7] $end
$var wire 1 w rectified [6] $end
$var wire 1 x rectified [5] $end
$var wire 1 y rectified [4] $end
$var wire 1 z rectified [3] $end
$var wire 1 { rectified [2] $end
$var wire 1 | rectified [1] $end
$var wire 1 } rectified [0] $end
$var reg 32 ~ integrator [31:0] $end
$var reg 16 !! symbol_counter [15:0] $end
$var wire 1 "! averaged [31] $end
$var wire 1 #! averaged [30] $end
$var wire 1 $! averaged [29] $end
$var wire 1 %! averaged [28] $end
$var wire 1 &! averaged [27] $end
$var wire 1 '! averaged [26] $end
$var wire 1 (! averaged [25] $end
$var wire 1 )! averaged [24] $end
$var wire 1 *! averaged [23] $end
$var wire 1 +! averaged [22] $end
$var wire 1 ,! averaged [21] $end
$var wire 1 -! averaged [20] $end
$var wire 1 .! averaged [19] $end
$var wire 1 /! averaged [18] $end
$var wire 1 0! averaged [17] $end
$var wire 1 1! averaged [16] $end
$var wire 1 2! averaged [15] $end
$var wire 1 3! averaged [14] $end
$var wire 1 4! averaged [13] $end
$var wire 1 5! averaged [12] $end
$var wire 1 6! averaged [11] $end
$var wire 1 7! averaged [10] $end
$var wire 1 8! averaged [9] $end
$var wire 1 9! averaged [8] $end
$var wire 1 :! averaged [7] $end
$var wire 1 ;! averaged [6] $end
$var wire 1 <! averaged [5] $end
$var wire 1 =! averaged [4] $end
$var wire 1 >! averaged [3] $end
$var wire 1 ?! averaged [2] $end
$var wire 1 @! averaged [1] $end
$var wire 1 A! averaged [0] $end

$scope module rectifier $end
$var wire 1 9 ac_signal [15] $end
$var wire 1 : ac_signal [14] $end
$var wire 1 ; ac_signal [13] $end
$var wire 1 < ac_signal [12] $end
$var wire 1 = ac_signal [11] $end
$var wire 1 > ac_signal [10] $end
$var wire 1 ? ac_signal [9] $end
$var wire 1 @ ac_signal [8] $end
$var wire 1 A ac_signal [7] $end
$var wire 1 B ac_signal [6] $end
$var wire 1 C ac_signal [5] $end
$var wire 1 D ac_signal [4] $end
$var wire 1 E ac_signal [3] $end
$var wire 1 F ac_signal [2] $end
$var wire 1 G ac_signal [1] $end
$var wire 1 H ac_signal [0] $end
$var wire 1 n dc_output [15] $end
$var wire 1 o dc_output [14] $end
$var wire 1 p dc_output [13] $end
$var wire 1 q dc_output [12] $end
$var wire 1 r dc_output [11] $end
$var wire 1 s dc_output [10] $end
$var wire 1 t dc_output [9] $end
$var wire 1 u dc_output [8] $end
$var wire 1 v dc_output [7] $end
$var wire 1 w dc_output [6] $end
$var wire 1 x dc_output [5] $end
$var wire 1 y dc_output [4] $end
$var wire 1 z dc_output [3] $end
$var wire 1 { dc_output [2] $end
$var wire 1 | dc_output [1] $end
$var wire 1 } dc_output [0] $end
$upscope $end
$upscope $end
$upscope $end
$upscope $end
$enddefinitions $end
#0
$dumpvars
0"
0#
b0 $
b0 Z
b0 [
b0 \
bx c
b0 d
0l
0m
b0 ~
b0 !!
b10100 !
b110001 Y
b10111110101111000010000000 _
b11110100001001000000 `
b100000 a
b101000111101011100001010001 b
b110010 j
b10011100010000 k
0%
0&
xH
xG
xF
xE
xD
xC
xB
xA
x@
x?
x>
x=
x<
x;
x:
x9
xX
xW
xV
xU
xT
xS
xR
xQ
xP
xO
xN
xM
xL
xK
xJ
xI
0]
1^
0i
0h
0g
0f
0e
x}
x|
x{
xz
xy
xx
xw
xv
xu
xt
xs
xr
xq
xp
xo
xn
0A!
0@!
0?!
0>!
0=!
0<!
0;!
0:!
09!
08!
07!
06!
05!
04!
03!
02!
01!
00!
0/!
0.!
0-!
0,!
0+!
0*!
0)!
0(!
0'!
0&!
0%!
0$!
0#!
0"!
08
07
06
05
04
03
02
01
00
0/
0.
0-
0,
0+
0*
0)
0(
0'
$end
#10000
1"
1'
b0 c
0X
0W
0V
0U
0T
0S
0R
0Q
0P
0O
0N
0M
0L
0K
0J
0I
0H
0G
0F
0E
0D
0C
0B
0A
0@
0?
0>
0=
0<
0;
0:
09
0}
0|
0{
0z
0y
0x
0w
0v
0u
0t
0s
0r
0q
0p
0o
0n
#20000
0"
0'
#30000
1"
1'
#40000
0"
0'
#50000
1"
1'
#60000
0"
0'
#70000
1"
1'
#80000
0"
0'
#90000
1"
1'
#100000
1#
0"
1(
0'
#110000
1"
1'
b1 \
b101000111101011100001010001 d
b1 !!
#120000
0"
0'
#130000
1"
1'
b10 \
b1010001111010111000010100010 d
b10 !!
1i
#140000
0"
0'
#150000
1"
1'
b11 \
b1111010111000010100011110011 d
b1100011111001 c
b11 !!
1X
1U
1T
1S
1R
1Q
1M
1L
1H
1E
1D
1C
1B
1A
1=
1<
1}
1z
1y
1x
1w
1v
1r
1q
#160000
0"
0'
#170000
1"
1'
b100 \
b10100011110101110000101000100 d
b1100011111001 ~
b100 !!
1A!
1@!
1?!
1>!
1=!
1<!
1;!
0i
1h
#180000
0"
0'
#190000
1"
1'
b101 \
b11001100110011001100110010101 d
b11000011111011 c
b11000111110010 ~
b101 !!
1:!
1W
0M
1K
1i
1G
0=
1;
1|
0r
1p
#200000
0"
0'
#210000
1"
1'
b110 \
b11110101110000101000111100110 d
b110001011101101 ~
b110 !!
b100011100011100 c
0X
0W
1V
0S
0R
0Q
1P
1O
1N
0L
0K
1J
0A!
0?!
19!
0H
0G
1F
0C
0B
0A
1@
1?
1>
0<
0;
1:
0}
0|
1{
0x
0w
0v
1u
1t
1s
0q
0p
1o
#220000
0"
0'
#230000
1"
1'
b111 \
b100011110101110000101000110111 d
b1010101000001001 ~
b111 !!
1?!
0>!
0=!
0:!
18!
0i
0h
1g
#240000
0"
0'
#250000
1"
1'
b1000 \
b101000111101011100001010001000 d
b101101010000010 c
b1111000100100101 ~
b1000 !!
0?!
1=!
0<!
1:!
09!
08!
17!
1W
0V
0U
0T
1Q
0P
0N
1M
1L
1i
1G
0F
0E
0D
1A
0@
0>
1=
1<
1|
0{
0z
0y
1v
0u
0s
1r
1q
#260000
0"
0'
#270000
1"
1'
b1001 \
b101110000101000111101011011001 d
b10100101110100111 ~
b1001 !!
b110101001101101 c
1X
0W
1V
1U
1S
1R
0Q
0L
1K
0=!
1<!
0;!
18!
1H
0G
1F
1E
1C
1B
0A
0<
1;
1}
0|
1{
1z
1x
1w
0v
0q
1p
#280000
0"
0'
#290000
1"
1'
b1010 \
b110011001100110011001100101010 d
b11011011000010100 ~
b1010 !!
0<!
1;!
08!
07!
16!
0i
1h
#300000
0"
0'
#310000
1"
1'
b1011 \
b111000010100011110101101111011 d
b111011001000001 c
b100010000010000001 ~
b1011 !!
1A!
1<!
18!
0V
0U
0S
1N
0M
1L
1i
0F
0E
0C
1>
0=
1<
0{
0z
0x
1s
0r
1q
#320000
0"
0'
#330000
1"
1'
b1100 \
b111101011100001010001111001100 d
b101001011011000010 ~
b1100 !!
b111110110001001 c
1U
0R
1Q
1P
0O
1M
0@!
0<!
0:!
19!
08!
17!
1E
0B
1A
1@
0?
1=
1z
0w
1v
1u
0t
1r
#340000
0"
0'
#350000
1"
1'
b1101 \
b1000010100011110101110000011101 d
b110001010001001011 ~
b1101 !!
0A!
1?!
1:!
18!
0i
0h
0g
1f
#360000
0"
0'
#370000
1"
1'
b1110 \
b1000111101011100001010001101110 d
b111111111110110 c
b111001000111010100 ~
b1110 !!
1@!
0:!
09!
07!
06!
15!
0X
1W
1V
0U
1T
1S
1R
1O
0H
1G
1F
0E
1D
1C
1B
1?
0}
1|
1{
0z
1y
1x
1w
1t
#380000
0"
0'
#390000
1"
1'
b1111 \
b1001100110011001100110010111111 d
b1000001000111001010 ~
b1111 !!
1A!
0@!
1=!
1:!
08!
17!
1i
#400000
0"
0'
#410000
1"
1'
b10000 \
b1010001111010111000010100010000 d
b111110110001001 c
b1001001000111000000 ~
b10000 !!
0=!
1<!
0:!
19!
18!
1X
0W
0V
1U
0T
0S
0R
0O
0i
1h
1H
0G
0F
1E
0D
0C
0B
0?
1}
0|
0{
1z
0y
0x
0w
0t
#420000
0"
0'
#430000
1"
1'
b10001 \
b1010111000010100011110101100001 d
b1010000111101001001 ~
b10001 !!
b111011001000001 c
0U
1R
0Q
0P
1O
0M
1@!
1:!
08!
07!
16!
0E
1B
0A
0@
1?
0=
0z
1w
0v
0u
1t
0r
#440000
0"
0'
#450000
1"
1'
b10010 \
b1011100001010001111010110110010 d
b1011000010110001010 ~
b10010 !!
0@!
0<!
0:!
09!
17!
1i
#460000
0"
0'
#470000
1"
1'
b10011 \
b1100001010001111010111000000011 d
b110101001101101 c
b1011111101111001011 ~
b10011 !!
0A!
1@!
0?!
1<!
0;!
1:!
18!
1V
1U
1S
0N
1M
0L
0i
0h
1g
1F
1E
1C
0>
1=
0<
1{
1z
1x
0s
1r
0q
#480000
0"
0'
#490000
1"
1'
b10100 \
b1100110011001100110011001010100 d
b1100110011000111000 ~
b10100 !!
b101101010000010 c
0X
1W
0V
0U
0S
0R
1Q
1L
0K
1A!
0<!
1;!
08!
07!
06!
05!
14!
0H
1G
0F
0E
0C
0B
1A
1<
0;
0}
1|
0{
0z
0x
0w
1v
1q
0p
#500000
0"
0'
#510000
1"
1'
b10101 \
b1101011100001010001111010100101 d
b1101100000010111010 ~
b10101 !!
1=!
0;!
18!
1i
#520000
0"
0'
#530000
1"
1'
b10110 \
b1110000101000111101011011110110 d
b100011100011100 c
b1110001101100111100 ~
b10110 !!
0A!
0=!
1<!
1;!
0:!
08!
17!
0W
1V
1U
1T
0Q
1P
1N
0M
0L
0i
1h
0G
1F
1E
1D
0A
1@
1>
0=
0<
0|
1{
1z
1y
0v
1u
1s
0r
0q
#540000
0"
0'
#550000
1"
1'
b10111 \
b1110101110000101000111101000111 d
b1110110001001011000 ~
b10111 !!
b11000011111011 c
1X
1W
0V
1S
1R
1Q
0P
0O
0N
1L
1K
0J
1?!
1>!
0<!
1:!
19!
1H
1G
0F
1C
1B
1A
0@
0?
0>
1<
1;
0:
1}
1|
0{
1x
1w
1v
0u
0t
0s
1q
1p
0o
#560000
0"
0'
#570000
1"
1'
b11000 \
b1111010111000010100011110011000 d
b1111001001101010011 ~
b11000 !!
1A!
0@!
0?!
09!
18!
1i
#580000
0"
0'
#590000
1"
1'
b11001 \
b1111111111111111111111111101001 d
b1100011111001 c
b1111100010001001110 ~
b11001 !!
0A!
1?!
0>!
19!
0W
1M
0K
0G
1=
0;
0|
1r
0p
#600000
0"
0'
#610000
1"
1'
b11010 \
b10000101000111101011100000111010 d
b1111101110101000111 ~
b11010 !!
1A!
1@!
0?!
0:!
09!
08!
07!
16!
0i
0h
0g
0f
1e
#620000
0"
0'
#630000
1"
1'
b11011 \
b10001010001111010111000010001011 d
b0 c
b1111111011001000000 ~
b11011 !!
1:!
0X
0U
0T
0S
0R
0Q
0M
0L
1i
0H
0E
0D
0C
0B
0A
0=
0<
0}
0z
0y
0x
0w
0v
0r
0q
#640000
0"
0'
#650000
1"
1'
b11100 \
b10001111010111000010100011011100 d
b11100 !!
b1110011100000111 c
1X
1W
1V
1P
1O
1N
1K
1J
1I
1H
1G
1F
1@
1?
1>
1;
1:
19
1z
1y
1x
1w
1v
1r
1q
#660000
0"
0'
#670000
1"
1'
b11101 \
b10010100011110101110000100101101 d
b10000000111100111000 ~
b11101 !!
0:!
19!
0i
1h
#680000
0"
0'
#690000
1"
1'
b11110 \
b10011001100110011001100101111110 d
b1100111100000101 c
b10000010100000110000 ~
b11110 !!
1:!
0W
1M
0K
1i
0G
1=
0;
1|
0r
1p
#700000
0"
0'
#710000
1"
1'
b11111 \
b10011110101110000101000111001111 d
b10000101100100101010 ~
b11111 !!
b1011100011100100 c
0X
1S
1R
1Q
0P
0O
0N
1L
1K
0J
0A!
1?!
1>!
1=!
1<!
0;!
09!
18!
0H
1C
1B
1A
0@
0?
0>
1<
1;
0:
1}
0x
0w
0v
1u
1t
1s
0q
0p
1o
#720000
0"
0'
#730000
1"
1'
b100000 \
b10100011110101110000101000100000 d
b10001010000001000101 ~
b100000 !!
0?!
0=!
0:!
08!
17!
0i
0h
1g
#740000
0"
0'
#750000
1"
1'
b100001 \
b10101000111101011100001001110001 d
b1010010101111110 c
b10001110011101100000 ~
b100001 !!
1?!
0>!
1=!
0<!
1:!
19!
1W
1U
1T
0Q
1P
1N
0M
0L
1i
1G
1E
1D
0A
1@
1>
0=
0<
0|
0z
0y
1v
0u
0s
1r
1q
#760000
0"
0'
#770000
1"
1'
b100010 \
b10101110000101000111101011000010 d
b10010100000111100001 ~
b100010 !!
b1001010110010011 c
1X
0V
0U
0S
0R
1Q
1L
0K
1A!
0@!
0=!
1<!
1;!
0:!
18!
1H
0F
0E
0C
0B
1A
1<
0;
0}
1{
1z
1x
1w
0v
0q
1p
#780000
0"
0'
#790000
1"
1'
b100011 \
b10110011001100110011001100010011 d
b10011010110001001101 ~
b100011 !!
0A!
1@!
0<!
0;!
1:!
08!
07!
06!
15!
0i
1h
#800000
0"
0'
#810000
1"
1'
b100100 \
b10111000010100011110101101100100 d
b1000100110111111 c
b10100001011010111001 ~
b100100 !!
1A!
1<!
18!
1V
1U
1S
0N
1M
0L
1i
1F
1E
1C
0>
1=
0<
0{
0z
0x
1s
0r
1q
#820000
0"
0'
#830000
1"
1'
b100101 \
b10111101011100001010001110110101 d
b10101000110011111001 ~
b100101 !!
b1000001001110111 c
0U
1R
0Q
0P
1O
0M
0A!
0@!
0<!
0:!
09!
17!
0E
1B
0A
0@
1?
0=
1z
0w
1v
1u
0t
1r
#840000
0"
0'
#850000
1"
1'
b100110 \
b11000010100011110101110000000110 d
b10110000101010000001 ~
b100110 !!
1A!
1@!
1:!
08!
07!
16!
0i
0h
0g
1f
#860000
0"
0'
#870000
1"
1'
b100111 \
b11000111101011100001010001010111 d
b1000000000001010 c
b10111000100000001001 ~
b100111 !!
0A!
0?!
1>!
0:!
19!
18!
0X
0V
1U
0T
0S
0R
0O
0H
0F
1E
0D
0C
0B
0?
1}
1{
0z
1y
1x
1w
1t
#880000
0"
0'
